api_of_things_client/__init__.py
api_of_things_client/api.py
api_of_things_client/models.py
api_of_things_client/models/__init__.py
api_of_things_client/models/api.py
api_of_things_client/models/geojson.py
api_of_things-0.0.12.dist-info/LICENSE
api_of_things-0.0.12.dist-info/METADATA
api_of_things-0.0.12.dist-info/WHEEL
api_of_things-0.0.12.dist-info/top_level.txt
api_of_things-0.0.12.dist-info/RECORD
